LICENSE
Logic_Py/__init__.py
Logic_Py/arithmatic_gates.py
Logic_Py/basic_gates.py
Logic_Py/combinational_gates.py
Logic_Py/Hello_World.py
Logic_Py/Logic_circuits.py
Logic_Py/plotting.py
Logic_Py/secondary_gates.py
logic_py-0.4.3.dist-info/LICENSE
logic_py-0.4.3.dist-info/WHEEL
logic_py-0.4.3.dist-info/METADATA
logic_py-0.4.3.dist-info/RECORD
