Metadata-Version: 2.1
Name: logic-py
Version: 0.4.3
Summary: Python Package to realize combinational logic gates
Home-page: https://github.com/Vishwesh-Vishwesh/Logic_Py
License: Apache 2.0
Keywords: python,Logic gates
Author: Vishwesh
Author-email: vishwesh.arush@gmail.com
Requires-Python: >=3.0,<4.0
Classifier: License :: Other/Proprietary License
Classifier: Programming Language :: Python :: 3
Classifier: Programming Language :: Python :: 3.4
Classifier: Programming Language :: Python :: 3.5
Classifier: Programming Language :: Python :: 3.6
Classifier: Programming Language :: Python :: 3.7
Classifier: Programming Language :: Python :: 3.8
Classifier: Programming Language :: Python :: 3.9
Requires-Dist: numpy (>=1.0,<2.0)
Project-URL: Repository, https://github.com/Vishwesh-Vishwesh/Logic_Py
